examples/__init__.py
examples/data.py
examples/reduce_circles.py
examples/reduce_moon.py
grease/__init__.py
grease/_cluster.py
grease/_metrics.py
grease/_reduction.py
grease/_utils.py
grease/_losses/__init__.py
grease/_losses/_spectralnet_loss.py
grease/_models/__init__.py
grease/_models/_ae_model.py
grease/_models/_spectralnet_model.py
grease/_trainers/__init__.py
grease/_trainers/_ae_trainer.py
grease/_trainers/_spectralnet_trainer.py
grease/_trainers/_trainer.py
spectralnet/__init__.py
spectralnet/_cluster.py
spectralnet/_metrics.py
spectralnet/_reduction.py
spectralnet/_utils.py
spectralnet/_losses/__init__.py
spectralnet/_losses/_spectralnet_loss.py
spectralnet/_models/__init__.py
spectralnet/_models/_ae_model.py
spectralnet/_models/_spectralnet_model.py
spectralnet/_trainers/__init__.py
spectralnet/_trainers/_ae_trainer.py
spectralnet/_trainers/_spectralnet_trainer.py
spectralnet/_trainers/_trainer.py
src/__init__.py
src/grease/__init__.py
src/grease/_cluster.py
src/grease/_metrics.py
src/grease/_reduction.py
src/grease/_utils.py
src/grease/_losses/__init__.py
src/grease/_losses/_spectralnet_loss.py
src/grease/_models/__init__.py
src/grease/_models/_ae_model.py
src/grease/_models/_spectralnet_model.py
src/grease/_trainers/__init__.py
src/grease/_trainers/_ae_trainer.py
src/grease/_trainers/_spectralnet_trainer.py
src/grease/_trainers/_trainer.py
src/spectralnet/__init__.py
src/spectralnet/_cluster.py
src/spectralnet/_metrics.py
src/spectralnet/_reduction.py
src/spectralnet/_utils.py
src/spectralnet/_losses/__init__.py
src/spectralnet/_losses/_spectralnet_loss.py
src/spectralnet/_models/__init__.py
src/spectralnet/_models/_ae_model.py
src/spectralnet/_models/_spectralnet_model.py
src/spectralnet/_trainers/__init__.py
src/spectralnet/_trainers/_ae_trainer.py
src/spectralnet/_trainers/_spectralnet_trainer.py
src/spectralnet/_trainers/_trainer.py
src/tests/__init__.py
tests/__init__.py
grease_embeddings-0.1.5.dist-info/LICENSE.md
grease_embeddings-0.1.5.dist-info/METADATA
grease_embeddings-0.1.5.dist-info/WHEEL
grease_embeddings-0.1.5.dist-info/top_level.txt
grease_embeddings-0.1.5.dist-info/RECORD
