Metadata-Version: 2.1
Name: grease-embeddings
Version: 0.1.5
Summary: Generalizable and Efficient Approximate Spectral Embeddings
Home-page: https://github.com/TheNirnir/GrEASE
Author: Nir Ben-Ari
Author-email: nirnirba@gmail.com
Classifier: Programming Language :: Python :: 3
Classifier: License :: OSI Approved :: MIT License
Classifier: Operating System :: OS Independent
Requires-Python: >=3.9
License-File: LICENSE.md
